src/__init__.py
src/actions.py
src/parser.py
src/search.py
devHelper-1.0.0.dist-info/LICENSE
devHelper-1.0.0.dist-info/METADATA
devHelper-1.0.0.dist-info/WHEEL
devHelper-1.0.0.dist-info/entry_points.txt
devHelper-1.0.0.dist-info/top_level.txt
devHelper-1.0.0.dist-info/RECORD
