Metadata-Version: 2.1
Name: devHelper
Version: 1.0.0
Summary: Dev Package for Dev Helper.
Home-page: https://github.com/luigicfh/devHelper
Author: Luis Moreno
Author-email: luis.cfh.90@gmail.com
License: MIT
Keywords: Dev Package for Dev Helper.
Platform: UNKNOWN
Classifier: Programming Language :: Python :: 3
Classifier: License :: OSI Approved :: MIT License
Classifier: Operating System :: OS Independent
License-File: LICENSE
Requires-Dist: autopep8 (==1.6.0)
Requires-Dist: beautifulsoup4 (==4.10.0)
Requires-Dist: bs4 (==0.0.1)
Requires-Dist: certifi (==2021.10.8)
Requires-Dist: charset-normalizer (==2.0.12)
Requires-Dist: idna (==3.3)
Requires-Dist: pycodestyle (==2.8.0)
Requires-Dist: requests (==2.27.1)
Requires-Dist: soupsieve (==2.3.1)
Requires-Dist: toml (==0.10.2)
Requires-Dist: urllib3 (==1.26.9)
